droidhack/__init__.py
droidhack/_utils.py
droidhack/devfs.py
droidhack/procfs.py
droidhack-1.3.dist-info/LICENSE
droidhack-1.3.dist-info/METADATA
droidhack-1.3.dist-info/WHEEL
droidhack-1.3.dist-info/top_level.txt
droidhack-1.3.dist-info/RECORD
