Metadata-Version: 2.1
Name: droidhack
Version: 1.3
Summary: A toolkit that provides easy access with procfs and devfs
Home-page: https://github.com/DKingAlpha/droidhack
Author: DKing
Author-email: dking@tot.im
License: UNKNOWN
Platform: UNKNOWN
Classifier: Programming Language :: Python :: 3
Classifier: License :: OSI Approved :: GNU Lesser General Public License v3 (LGPLv3)
Classifier: Operating System :: Android
Classifier: Operating System :: POSIX
Classifier: Topic :: System
Classifier: Topic :: Security
Classifier: Topic :: Software Development :: Embedded Systems
Requires-Python: >=3.7
License-File: LICENSE
